allure.py
allure_commons_il/__init__.py
allure_commons_il/_allure.py
allure_commons_il/_core.py
allure_commons_il/_hooks.py
allure_commons_il/lifecycle.py
allure_commons_il/logger.py
allure_commons_il/mapping.py
allure_commons_il/model2.py
allure_commons_il/reporter.py
allure_commons_il/types.py
allure_commons_il/utils.py
allure_python_commons_il-0.0.1.dist-info/METADATA
allure_python_commons_il-0.0.1.dist-info/WHEEL
allure_python_commons_il-0.0.1.dist-info/top_level.txt
allure_python_commons_il-0.0.1.dist-info/RECORD
